helmut4/client/__init__.py
helmut4/client/client.py
helmut4/client/exceptions.py
helmut4/client/modules/__init__.py
helmut4/client/modules/_base.py
helmut4/client/modules/assets.py
helmut4/client/modules/cronjob.py
helmut4/client/modules/groups.py
helmut4/client/modules/jobs.py
helmut4/client/modules/languages.py
helmut4/client/modules/license.py
helmut4/client/modules/metadata.py
helmut4/client/modules/preferences.py
helmut4/client/modules/projects.py
helmut4/client/modules/streams.py
helmut4/client/modules/users.py
helmut4_client-2025.6b1.dist-info/METADATA
helmut4_client-2025.6b1.dist-info/WHEEL
helmut4_client-2025.6b1.dist-info/top_level.txt
helmut4_client-2025.6b1.dist-info/RECORD
