Metadata-Version: 2.4
Name: helmut4-client
Version: 2025.6b1
Summary: A Python client library for interacting with the Helmut4 API.
Author-email: "Brian F. Summa" <brian.f.summa@chesa.com>
Maintainer-email: Product Team <product@chesa.com>, "Chesapeake Systems, LLC" <info@chesa.com>
License: MIT
Project-URL: Homepage, https://chesa.com/
Project-URL: Repository, https://bitbucket.org/chesa/helmut4-client/
Keywords: Helmut4,API,client,MoovIT,workflow management,project-based workflows,project assets,Adobe,Premiere Pro,After Effects
Classifier: Development Status :: 4 - Beta
Classifier: Intended Audience :: Developers
Classifier: License :: OSI Approved :: MIT License
Classifier: Programming Language :: Python :: 3
Classifier: Programming Language :: Python :: 3.11
Classifier: Programming Language :: Python :: 3.12
Classifier: Programming Language :: Python :: 3.13
Requires-Python: >=3.11
Requires-Dist: Requests>=2.25.0
Provides-Extra: dev
Requires-Dist: black~=25.1.0; extra == "dev"
Requires-Dist: flake8~=7.2.0; extra == "dev"
Requires-Dist: Flake8-pyproject~=1.2.3; extra == "dev"
Requires-Dist: isort~=6.0.1; extra == "dev"
Requires-Dist: mypy~=1.15.0; extra == "dev"
Requires-Dist: pycln~=2.5.0; extra == "dev"
Requires-Dist: pylint~=3.3.6; extra == "dev"
Requires-Dist: pytest~=8.3.5; extra == "dev"
Requires-Dist: pytest-asyncio~=0.26.0; extra == "dev"
Requires-Dist: pytest-cov~=6.1.1; extra == "dev"
Requires-Dist: pytest-mock~=3.14.0; extra == "dev"
Requires-Dist: ruff~=0.11.7; extra == "dev"
Requires-Dist: setuptools>=77.0.3; extra == "dev"
Requires-Dist: toml-sort~=0.24.2; extra == "dev"
Requires-Dist: uv~=0.7.2; extra == "dev"
Requires-Dist: yapf~=0.43.0; extra == "dev"
